commonsearchai/__init__.py
commonsearchai/__main__.py
commonsearchai/cli.py
commonsearchai-0.1.0.dist-info/METADATA
commonsearchai-0.1.0.dist-info/WHEEL
commonsearchai-0.1.0.dist-info/entry_points.txt
commonsearchai-0.1.0.dist-info/top_level.txt
commonsearchai-0.1.0.dist-info/RECORD
