Metadata-Version: 2.1
Name: commonsearchai
Version: 0.1.0
Summary: Fundamentals functions for azure search ai
Home-page: https://www.pomiager.com/commonsearchai
Author: Sandro Vecchiarelli
Author-email: sandro.vecchiarelli@pomiager.com
License: The Unlicense
Project-URL: Documentation, https://pomiagerbo@dev.azure.com/pomiagerbo/AI_CommonSearchLib/_git/AI_CommonSearchLib
Project-URL: Source, https://pomiagerbo@dev.azure.com/pomiagerbo/AI_CommonSearchLib/_git/AI_CommonSearchLib
Classifier: Development Status :: 3 - Alpha
Classifier: Intended Audience :: Developers
Classifier: Programming Language :: Python :: 3.11
Classifier: Topic :: Utilities
Requires-Python: >=3.10, <3.12
Requires-Dist: requests
Requires-Dist: pandas >=2.0
Requires-Dist: azure-search
Requires-Dist: azure-search-documents
